[
  {
    "nom": "Toulouse",
    "slug": "toulouse",
    "codeInsee": "31555",
    "codePostal": "31000",
    "population": 514819,
    "latitude": 43.6007,
    "longitude": 1.4328,
    "altitude": 141,
    "logements": 270957,
    "logementsMaison": 16,
    "prixM2Moyen": 4020,
    "vehiculesElectriques": 22375,
    "croissanceVE": 29,
    "bornesPubliques": 459,
    "intercommunalite": "Toulouse Métropole",
    "canton": "Toulouse",
    "distanceBordeaux": 1,
    "densiteBornes": 0.9,
    "profilCommune": "métropole régionale",
    "marcheImmobilier": "très premium",
    "tauxMaisonLabel": "très dense (collectif)"
  },
  {
    "nom": "Colomiers",
    "slug": "colomiers",
    "codeInsee": "31149",
    "codePostal": "31770",
    "population": 40882,
    "latitude": 43.6116,
    "longitude": 1.3245,
    "altitude": 160,
    "logements": 19015,
    "logementsMaison": 39,
    "prixM2Moyen": 3280,
    "vehiculesElectriques": 1541,
    "croissanceVE": 21,
    "bornesPubliques": 37,
    "intercommunalite": "Toulouse Métropole",
    "canton": "Colomiers",
    "distanceBordeaux": 9.7,
    "densiteBornes": 0.9,
    "profilCommune": "grande ville",
    "marcheImmobilier": "haut de gamme",
    "tauxMaisonLabel": "majoritairement collectif"
  },
  {
    "nom": "Tournefeuille",
    "slug": "tournefeuille",
    "codeInsee": "31557",
    "codePostal": "31170",
    "population": 30168,
    "latitude": 43.5747,
    "longitude": 1.3338,
    "altitude": 146,
    "logements": 13408,
    "logementsMaison": 66,
    "prixM2Moyen": 3950,
    "vehiculesElectriques": 1420,
    "croissanceVE": 20,
    "bornesPubliques": 29,
    "intercommunalite": "Toulouse Métropole",
    "canton": "Tournefeuille",
    "distanceBordeaux": 9.5,
    "densiteBornes": 1,
    "profilCommune": "grande ville",
    "marcheImmobilier": "très premium",
    "tauxMaisonLabel": "majoritairement pavillonnaire"
  },
  {
    "nom": "Blagnac",
    "slug": "blagnac",
    "codeInsee": "31069",
    "codePostal": "31700",
    "population": 27604,
    "latitude": 43.641,
    "longitude": 1.377,
    "altitude": 145,
    "logements": 12268,
    "logementsMaison": 38,
    "prixM2Moyen": 3910,
    "vehiculesElectriques": 1126,
    "croissanceVE": 25,
    "bornesPubliques": 26,
    "intercommunalite": "Toulouse Métropole",
    "canton": "Blagnac",
    "distanceBordeaux": 6.8,
    "densiteBornes": 0.9,
    "profilCommune": "ville moyenne",
    "marcheImmobilier": "très premium",
    "tauxMaisonLabel": "majoritairement collectif"
  },
  {
    "nom": "Muret",
    "slug": "muret",
    "codeInsee": "31395",
    "codePostal": "31600",
    "population": 26079,
    "latitude": 43.4407,
    "longitude": 1.2987,
    "altitude": 161,
    "logements": 11591,
    "logementsMaison": 63,
    "prixM2Moyen": 3260,
    "vehiculesElectriques": 1031,
    "croissanceVE": 29,
    "bornesPubliques": 24,
    "intercommunalite": "Le Muretain Agglo",
    "canton": "Muret",
    "distanceBordeaux": 21.7,
    "densiteBornes": 0.9,
    "profilCommune": "ville moyenne",
    "marcheImmobilier": "haut de gamme",
    "tauxMaisonLabel": "majoritairement pavillonnaire"
  },
  {
    "nom": "Plaisance-du-Touch",
    "slug": "plaisance-du-touch",
    "codeInsee": "31424",
    "codePostal": "31830",
    "population": 21079,
    "latitude": 43.5626,
    "longitude": 1.2833,
    "altitude": 162,
    "logements": 9368,
    "logementsMaison": 66,
    "prixM2Moyen": 3020,
    "vehiculesElectriques": 898,
    "croissanceVE": 28,
    "bornesPubliques": 22,
    "intercommunalite": "Toulouse Métropole",
    "canton": "Plaisance-du-Touch",
    "distanceBordeaux": 13.8,
    "densiteBornes": 1,
    "profilCommune": "ville moyenne",
    "marcheImmobilier": "intermédiaire",
    "tauxMaisonLabel": "majoritairement pavillonnaire"
  },
  {
    "nom": "Cugnaux",
    "slug": "cugnaux",
    "codeInsee": "31157",
    "codePostal": "31270",
    "population": 20662,
    "latitude": 43.5446,
    "longitude": 1.3432,
    "altitude": 156,
    "logements": 9183,
    "logementsMaison": 62,
    "prixM2Moyen": 3170,
    "vehiculesElectriques": 867,
    "croissanceVE": 21,
    "bornesPubliques": 20,
    "intercommunalite": "Toulouse Métropole",
    "canton": "Cugnaux",
    "distanceBordeaux": 10.5,
    "densiteBornes": 1,
    "profilCommune": "ville moyenne",
    "marcheImmobilier": "intermédiaire",
    "tauxMaisonLabel": "majoritairement pavillonnaire"
  },
  {
    "nom": "Balma",
    "slug": "balma",
    "codeInsee": "31044",
    "codePostal": "31130",
    "population": 17772,
    "latitude": 43.6108,
    "longitude": 1.5037,
    "altitude": 185,
    "logements": 7899,
    "logementsMaison": 68,
    "prixM2Moyen": 4480,
    "vehiculesElectriques": 947,
    "croissanceVE": 32,
    "bornesPubliques": 20,
    "intercommunalite": "Toulouse Métropole",
    "canton": "Balma",
    "distanceBordeaux": 4.8,
    "densiteBornes": 1.1,
    "profilCommune": "ville moyenne",
    "marcheImmobilier": "très premium",
    "tauxMaisonLabel": "majoritairement pavillonnaire"
  },
  {
    "nom": "Castanet-Tolosan",
    "slug": "castanet-tolosan",
    "codeInsee": "31113",
    "codePostal": "31320",
    "population": 15317,
    "latitude": 43.5083,
    "longitude": 1.5069,
    "altitude": 170,
    "logements": 6808,
    "logementsMaison": 66,
    "prixM2Moyen": 2850,
    "vehiculesElectriques": 673,
    "croissanceVE": 30,
    "bornesPubliques": 16,
    "intercommunalite": "Communauté de Communes du SICOVAL",
    "canton": "Castanet-Tolosan",
    "distanceBordeaux": 11.8,
    "densiteBornes": 1,
    "profilCommune": "ville moyenne",
    "marcheImmobilier": "intermédiaire",
    "tauxMaisonLabel": "majoritairement pavillonnaire"
  },
  {
    "nom": "Ramonville-Saint-Agne",
    "slug": "ramonville-saint-agne",
    "codeInsee": "31446",
    "codePostal": "31520",
    "population": 15158,
    "latitude": 43.5438,
    "longitude": 1.4784,
    "altitude": 165,
    "logements": 6737,
    "logementsMaison": 49,
    "prixM2Moyen": 3950,
    "vehiculesElectriques": 639,
    "croissanceVE": 28,
    "bornesPubliques": 16,
    "intercommunalite": "Communauté de Communes du SICOVAL",
    "canton": "Ramonville-Saint-Agne",
    "distanceBordeaux": 7.3,
    "densiteBornes": 1.1,
    "profilCommune": "ville moyenne",
    "marcheImmobilier": "très premium",
    "tauxMaisonLabel": "mixte pavillonnaire-collectif"
  },
  {
    "nom": "Saint-Orens-de-Gameville",
    "slug": "saint-orens-de-gameville",
    "codeInsee": "31506",
    "codePostal": "31650",
    "population": 14646,
    "latitude": 43.555,
    "longitude": 1.5332,
    "altitude": 151,
    "logements": 6509,
    "logementsMaison": 61,
    "prixM2Moyen": 2110,
    "vehiculesElectriques": 528,
    "croissanceVE": 23,
    "bornesPubliques": 14,
    "intercommunalite": "Toulouse Métropole",
    "canton": "Saint-Orens-de-Gameville",
    "distanceBordeaux": 9,
    "densiteBornes": 1,
    "profilCommune": "commune urbaine",
    "marcheImmobilier": "accessible",
    "tauxMaisonLabel": "majoritairement pavillonnaire"
  },
  {
    "nom": "Fonsorbes",
    "slug": "fonsorbes",
    "codeInsee": "31187",
    "codePostal": "31470",
    "population": 12954,
    "latitude": 43.5332,
    "longitude": 1.2429,
    "altitude": 158,
    "logements": 5757,
    "logementsMaison": 68,
    "prixM2Moyen": 2160,
    "vehiculesElectriques": 549,
    "croissanceVE": 27,
    "bornesPubliques": 13,
    "intercommunalite": "Le Muretain Agglo",
    "canton": "Fonsorbes",
    "distanceBordeaux": 18.1,
    "densiteBornes": 1,
    "profilCommune": "commune urbaine",
    "marcheImmobilier": "accessible",
    "tauxMaisonLabel": "majoritairement pavillonnaire"
  },
  {
    "nom": "L'Union",
    "slug": "l-union",
    "codeInsee": "31561",
    "codePostal": "31240",
    "population": 12638,
    "latitude": 43.6515,
    "longitude": 1.483,
    "altitude": 160,
    "logements": 5617,
    "logementsMaison": 67,
    "prixM2Moyen": 3890,
    "vehiculesElectriques": 612,
    "croissanceVE": 33,
    "bornesPubliques": 12,
    "intercommunalite": "Toulouse Métropole",
    "canton": "L'Union",
    "distanceBordeaux": 6.1,
    "densiteBornes": 0.9,
    "profilCommune": "commune urbaine",
    "marcheImmobilier": "très premium",
    "tauxMaisonLabel": "majoritairement pavillonnaire"
  },
  {
    "nom": "Saint-Gaudens",
    "slug": "saint-gaudens",
    "codeInsee": "31483",
    "codePostal": "31800",
    "population": 12139,
    "latitude": 43.1209,
    "longitude": 0.7254,
    "altitude": 405,
    "logements": 5395,
    "logementsMaison": 88,
    "prixM2Moyen": 1500,
    "vehiculesElectriques": 430,
    "croissanceVE": 28,
    "bornesPubliques": 16,
    "intercommunalite": "Communauté de Communes Cœur et Coteaux du Comminges",
    "canton": "Saint-Gaudens",
    "distanceBordeaux": 79.2,
    "densiteBornes": 1.3,
    "profilCommune": "commune urbaine",
    "marcheImmobilier": "très accessible",
    "tauxMaisonLabel": "très pavillonnaire"
  },
  {
    "nom": "Castelginest",
    "slug": "castelginest",
    "codeInsee": "31116",
    "codePostal": "31780",
    "population": 11271,
    "latitude": 43.698,
    "longitude": 1.4349,
    "altitude": 139,
    "logements": 5009,
    "logementsMaison": 64,
    "prixM2Moyen": 2370,
    "vehiculesElectriques": 452,
    "croissanceVE": 31,
    "bornesPubliques": 12,
    "intercommunalite": "Toulouse Métropole",
    "canton": "Castelginest",
    "distanceBordeaux": 10.4,
    "densiteBornes": 1.1,
    "profilCommune": "commune urbaine",
    "marcheImmobilier": "accessible",
    "tauxMaisonLabel": "majoritairement pavillonnaire"
  },
  {
    "nom": "Saint-Jean",
    "slug": "saint-jean",
    "codeInsee": "31488",
    "codePostal": "31240",
    "population": 11261,
    "latitude": 43.6641,
    "longitude": 1.5016,
    "altitude": 157,
    "logements": 5005,
    "logementsMaison": 67,
    "prixM2Moyen": 2230,
    "vehiculesElectriques": 475,
    "croissanceVE": 25,
    "bornesPubliques": 15,
    "intercommunalite": "Toulouse Métropole",
    "canton": "Saint-Jean",
    "distanceBordeaux": 8.1,
    "densiteBornes": 1.3,
    "profilCommune": "commune urbaine",
    "marcheImmobilier": "accessible",
    "tauxMaisonLabel": "majoritairement pavillonnaire"
  },
  {
    "nom": "Villeneuve-Tolosane",
    "slug": "villeneuve-tolosane",
    "codeInsee": "31588",
    "codePostal": "31270",
    "population": 11044,
    "latitude": 43.5273,
    "longitude": 1.3447,
    "altitude": 142,
    "logements": 4908,
    "logementsMaison": 67,
    "prixM2Moyen": 2100,
    "vehiculesElectriques": 424,
    "croissanceVE": 31,
    "bornesPubliques": 14,
    "intercommunalite": "Toulouse Métropole",
    "canton": "Villeneuve-Tolosane",
    "distanceBordeaux": 11.8,
    "densiteBornes": 1.3,
    "profilCommune": "commune urbaine",
    "marcheImmobilier": "accessible",
    "tauxMaisonLabel": "majoritairement pavillonnaire"
  },
  {
    "nom": "Seysses",
    "slug": "seysses",
    "codeInsee": "31547",
    "codePostal": "31600",
    "population": 10539,
    "latitude": 43.4971,
    "longitude": 1.2822,
    "altitude": 140,
    "logements": 4684,
    "logementsMaison": 65,
    "prixM2Moyen": 2230,
    "vehiculesElectriques": 413,
    "croissanceVE": 23,
    "bornesPubliques": 11,
    "intercommunalite": "Le Muretain Agglo",
    "canton": "Muret",
    "distanceBordeaux": 17.7,
    "densiteBornes": 1,
    "profilCommune": "commune urbaine",
    "marcheImmobilier": "accessible",
    "tauxMaisonLabel": "majoritairement pavillonnaire"
  },
  {
    "nom": "Auterive",
    "slug": "auterive",
    "codeInsee": "31033",
    "codePostal": "31190",
    "population": 10456,
    "latitude": 43.3579,
    "longitude": 1.4822,
    "altitude": 190,
    "logements": 4647,
    "logementsMaison": 63,
    "prixM2Moyen": 2180,
    "vehiculesElectriques": 403,
    "croissanceVE": 30,
    "bornesPubliques": 11,
    "intercommunalite": "Communauté de Communes du Bassin Auterivain",
    "canton": "Auterive",
    "distanceBordeaux": 27.6,
    "densiteBornes": 1.1,
    "profilCommune": "commune urbaine",
    "marcheImmobilier": "accessible",
    "tauxMaisonLabel": "majoritairement pavillonnaire"
  },
  {
    "nom": "Léguevin",
    "slug": "leguevin",
    "codeInsee": "31291",
    "codePostal": "31490",
    "population": 9945,
    "latitude": 43.5928,
    "longitude": 1.2353,
    "altitude": 140,
    "logements": 4420,
    "logementsMaison": 65,
    "prixM2Moyen": 2290,
    "vehiculesElectriques": 423,
    "croissanceVE": 32,
    "bornesPubliques": 12,
    "intercommunalite": "Communauté de Communes du Volvestre",
    "canton": "Léguevin",
    "distanceBordeaux": 16.9,
    "densiteBornes": 1.2,
    "profilCommune": "commune urbaine",
    "marcheImmobilier": "accessible",
    "tauxMaisonLabel": "majoritairement pavillonnaire"
  },
  {
    "nom": "Saint-Lys",
    "slug": "saint-lys",
    "codeInsee": "31499",
    "codePostal": "31470",
    "population": 9892,
    "latitude": 43.5106,
    "longitude": 1.2023,
    "altitude": 147,
    "logements": 4396,
    "logementsMaison": 57,
    "prixM2Moyen": 2220,
    "vehiculesElectriques": 412,
    "croissanceVE": 28,
    "bornesPubliques": 14,
    "intercommunalite": "Le Muretain Agglo",
    "canton": "Saint-Lys",
    "distanceBordeaux": 22.1,
    "densiteBornes": 1.4,
    "profilCommune": "commune urbaine",
    "marcheImmobilier": "accessible",
    "tauxMaisonLabel": "mixte pavillonnaire-collectif"
  },
  {
    "nom": "Frouzins",
    "slug": "frouzins",
    "codeInsee": "31203",
    "codePostal": "31270",
    "population": 9805,
    "latitude": 43.5218,
    "longitude": 1.3125,
    "altitude": 149,
    "logements": 4358,
    "logementsMaison": 59,
    "prixM2Moyen": 2440,
    "vehiculesElectriques": 340,
    "croissanceVE": 30,
    "bornesPubliques": 10,
    "intercommunalite": "Le Muretain Agglo",
    "canton": "Frouzins",
    "distanceBordeaux": 14.1,
    "densiteBornes": 1,
    "profilCommune": "commune urbaine",
    "marcheImmobilier": "accessible",
    "tauxMaisonLabel": "mixte pavillonnaire-collectif"
  },
  {
    "nom": "Portet-sur-Garonne",
    "slug": "portet-sur-garonne",
    "codeInsee": "31433",
    "codePostal": "31120",
    "population": 9782,
    "latitude": 43.5285,
    "longitude": 1.3995,
    "altitude": 137,
    "logements": 4348,
    "logementsMaison": 62,
    "prixM2Moyen": 2080,
    "vehiculesElectriques": 336,
    "croissanceVE": 32,
    "bornesPubliques": 12,
    "intercommunalite": "Toulouse Métropole",
    "canton": "Portet-sur-Garonne",
    "distanceBordeaux": 9.2,
    "densiteBornes": 1.2,
    "profilCommune": "commune urbaine",
    "marcheImmobilier": "accessible",
    "tauxMaisonLabel": "majoritairement pavillonnaire"
  },
  {
    "nom": "Revel",
    "slug": "revel",
    "codeInsee": "31451",
    "codePostal": "31250",
    "population": 9762,
    "latitude": 43.4679,
    "longitude": 1.9975,
    "altitude": 210,
    "logements": 4339,
    "logementsMaison": 87,
    "prixM2Moyen": 2290,
    "vehiculesElectriques": 446,
    "croissanceVE": 29,
    "bornesPubliques": 12,
    "intercommunalite": "Communauté de Communes Lauragais Revel Sorèzois",
    "canton": "Revel",
    "distanceBordeaux": 47.1,
    "densiteBornes": 1.2,
    "profilCommune": "commune urbaine",
    "marcheImmobilier": "accessible",
    "tauxMaisonLabel": "très pavillonnaire"
  },
  {
    "nom": "Aucamville",
    "slug": "aucamville",
    "codeInsee": "31022",
    "codePostal": "31140",
    "population": 9623,
    "latitude": 43.6714,
    "longitude": 1.4243,
    "altitude": 150,
    "logements": 4277,
    "logementsMaison": 60,
    "prixM2Moyen": 2290,
    "vehiculesElectriques": 418,
    "croissanceVE": 32,
    "bornesPubliques": 13,
    "intercommunalite": "Toulouse Métropole",
    "canton": "Aucamville",
    "distanceBordeaux": 7.6,
    "densiteBornes": 1.4,
    "profilCommune": "commune urbaine",
    "marcheImmobilier": "accessible",
    "tauxMaisonLabel": "majoritairement pavillonnaire"
  },
  {
    "nom": "Launaguet",
    "slug": "launaguet",
    "codeInsee": "31282",
    "codePostal": "31140",
    "population": 9173,
    "latitude": 43.6668,
    "longitude": 1.4579,
    "altitude": 147,
    "logements": 4077,
    "logementsMaison": 57,
    "prixM2Moyen": 2120,
    "vehiculesElectriques": 394,
    "croissanceVE": 31,
    "bornesPubliques": 11,
    "intercommunalite": "Toulouse Métropole",
    "canton": "Launaguet",
    "distanceBordeaux": 7,
    "densiteBornes": 1.2,
    "profilCommune": "commune urbaine",
    "marcheImmobilier": "accessible",
    "tauxMaisonLabel": "mixte pavillonnaire-collectif"
  },
  {
    "nom": "Grenade",
    "slug": "grenade",
    "codeInsee": "31232",
    "codePostal": "31330",
    "population": 9062,
    "latitude": 43.7702,
    "longitude": 1.2791,
    "altitude": 120,
    "logements": 4028,
    "logementsMaison": 66,
    "prixM2Moyen": 2330,
    "vehiculesElectriques": 325,
    "croissanceVE": 27,
    "bornesPubliques": 10,
    "intercommunalite": "Communauté de Communes des Hauts Tolosains",
    "canton": "Grenade",
    "distanceBordeaux": 22.7,
    "densiteBornes": 1.1,
    "profilCommune": "commune urbaine",
    "marcheImmobilier": "accessible",
    "tauxMaisonLabel": "majoritairement pavillonnaire"
  },
  {
    "nom": "Cornebarrieu",
    "slug": "cornebarrieu",
    "codeInsee": "31150",
    "codePostal": "31700",
    "population": 8978,
    "latitude": 43.649,
    "longitude": 1.3197,
    "altitude": 142,
    "logements": 3990,
    "logementsMaison": 67,
    "prixM2Moyen": 2350,
    "vehiculesElectriques": 337,
    "croissanceVE": 34,
    "bornesPubliques": 14,
    "intercommunalite": "Toulouse Métropole",
    "canton": "Blagnac",
    "distanceBordeaux": 11.2,
    "densiteBornes": 1.6,
    "profilCommune": "commune urbaine",
    "marcheImmobilier": "accessible",
    "tauxMaisonLabel": "majoritairement pavillonnaire"
  },
  {
    "nom": "Pibrac",
    "slug": "pibrac",
    "codeInsee": "31417",
    "codePostal": "31820",
    "population": 8977,
    "latitude": 43.6245,
    "longitude": 1.2584,
    "altitude": 144,
    "logements": 3990,
    "logementsMaison": 69,
    "prixM2Moyen": 2120,
    "vehiculesElectriques": 364,
    "croissanceVE": 22,
    "bornesPubliques": 14,
    "intercommunalite": "Toulouse Métropole",
    "canton": "Pibrac",
    "distanceBordeaux": 15.1,
    "densiteBornes": 1.6,
    "profilCommune": "commune urbaine",
    "marcheImmobilier": "accessible",
    "tauxMaisonLabel": "majoritairement pavillonnaire"
  },
  {
    "nom": "Beauzelle",
    "slug": "beauzelle",
    "codeInsee": "31056",
    "codePostal": "31700",
    "population": 8713,
    "latitude": 43.668,
    "longitude": 1.3753,
    "altitude": 146,
    "logements": 3872,
    "logementsMaison": 56,
    "prixM2Moyen": 2270,
    "vehiculesElectriques": 325,
    "croissanceVE": 30,
    "bornesPubliques": 11,
    "intercommunalite": "Toulouse Métropole",
    "canton": "Blagnac",
    "distanceBordeaux": 9,
    "densiteBornes": 1.3,
    "profilCommune": "commune urbaine",
    "marcheImmobilier": "accessible",
    "tauxMaisonLabel": "mixte pavillonnaire-collectif"
  },
  {
    "nom": "Saint-Jory",
    "slug": "saint-jory",
    "codeInsee": "31490",
    "codePostal": "31790",
    "population": 8662,
    "latitude": 43.7398,
    "longitude": 1.3539,
    "altitude": 135,
    "logements": 3850,
    "logementsMaison": 60,
    "prixM2Moyen": 2180,
    "vehiculesElectriques": 345,
    "croissanceVE": 33,
    "bornesPubliques": 11,
    "intercommunalite": "Communauté de Communes du Volvestre",
    "canton": "Saint-Jory",
    "distanceBordeaux": 16.7,
    "densiteBornes": 1.3,
    "profilCommune": "commune urbaine",
    "marcheImmobilier": "accessible",
    "tauxMaisonLabel": "majoritairement pavillonnaire"
  },
  {
    "nom": "La Salvetat-Saint-Gilles",
    "slug": "la-salvetat-saint-gilles",
    "codeInsee": "31526",
    "codePostal": "31880",
    "population": 8511,
    "latitude": 43.5768,
    "longitude": 1.2655,
    "altitude": 148,
    "logements": 3783,
    "logementsMaison": 58,
    "prixM2Moyen": 2400,
    "vehiculesElectriques": 303,
    "croissanceVE": 20,
    "bornesPubliques": 11,
    "intercommunalite": "Communauté de Communes du Volvestre",
    "canton": "La Salvetat-Saint-Gilles",
    "distanceBordeaux": 14.7,
    "densiteBornes": 1.3,
    "profilCommune": "commune urbaine",
    "marcheImmobilier": "accessible",
    "tauxMaisonLabel": "mixte pavillonnaire-collectif"
  },
  {
    "nom": "Aussonne",
    "slug": "aussonne",
    "codeInsee": "31032",
    "codePostal": "31840",
    "population": 7997,
    "latitude": 43.6841,
    "longitude": 1.3278,
    "altitude": 145,
    "logements": 3554,
    "logementsMaison": 55,
    "prixM2Moyen": 2050,
    "vehiculesElectriques": 300,
    "croissanceVE": 22,
    "bornesPubliques": 11,
    "intercommunalite": "Toulouse Métropole",
    "canton": "Aussonne",
    "distanceBordeaux": 12.9,
    "densiteBornes": 1.4,
    "profilCommune": "commune résidentielle",
    "marcheImmobilier": "accessible",
    "tauxMaisonLabel": "mixte pavillonnaire-collectif"
  },
  {
    "nom": "Castelnau-d'Estrétefonds",
    "slug": "castelnau-d-estretefonds",
    "codeInsee": "31118",
    "codePostal": "31620",
    "population": 7003,
    "latitude": 43.7956,
    "longitude": 1.3516,
    "altitude": 145,
    "logements": 3112,
    "logementsMaison": 55,
    "prixM2Moyen": 2040,
    "vehiculesElectriques": 243,
    "croissanceVE": 24,
    "bornesPubliques": 10,
    "intercommunalite": "Communauté de Communes du Frontonnais",
    "canton": "Castelnau-d'Estrétefonds",
    "distanceBordeaux": 22.5,
    "densiteBornes": 1.4,
    "profilCommune": "commune résidentielle",
    "marcheImmobilier": "accessible",
    "tauxMaisonLabel": "mixte pavillonnaire-collectif"
  },
  {
    "nom": "Escalquens",
    "slug": "escalquens",
    "codeInsee": "31169",
    "codePostal": "31750",
    "population": 6924,
    "latitude": 43.5201,
    "longitude": 1.5528,
    "altitude": 141,
    "logements": 3077,
    "logementsMaison": 66,
    "prixM2Moyen": 2410,
    "vehiculesElectriques": 310,
    "croissanceVE": 24,
    "bornesPubliques": 11,
    "intercommunalite": "Communauté de Communes du SICOVAL",
    "canton": "Escalquens",
    "distanceBordeaux": 12.8,
    "densiteBornes": 1.6,
    "profilCommune": "commune résidentielle",
    "marcheImmobilier": "accessible",
    "tauxMaisonLabel": "majoritairement pavillonnaire"
  },
  {
    "nom": "Merville",
    "slug": "merville",
    "codeInsee": "31341",
    "codePostal": "31330",
    "population": 6760,
    "latitude": 43.7227,
    "longitude": 1.2916,
    "altitude": 141,
    "logements": 3004,
    "logementsMaison": 66,
    "prixM2Moyen": 2060,
    "vehiculesElectriques": 302,
    "croissanceVE": 29,
    "bornesPubliques": 12,
    "intercommunalite": "Communauté de Communes des Hauts Tolosains",
    "canton": "Merville",
    "distanceBordeaux": 18,
    "densiteBornes": 1.8,
    "profilCommune": "commune résidentielle",
    "marcheImmobilier": "accessible",
    "tauxMaisonLabel": "majoritairement pavillonnaire"
  },
  {
    "nom": "Fronton",
    "slug": "fronton",
    "codeInsee": "31202",
    "codePostal": "31620",
    "population": 6671,
    "latitude": 43.8529,
    "longitude": 1.3714,
    "altitude": 145,
    "logements": 2965,
    "logementsMaison": 56,
    "prixM2Moyen": 2470,
    "vehiculesElectriques": 270,
    "croissanceVE": 24,
    "bornesPubliques": 12,
    "intercommunalite": "Communauté de Communes du Frontonnais",
    "canton": "Fronton",
    "distanceBordeaux": 28.2,
    "densiteBornes": 1.8,
    "profilCommune": "commune résidentielle",
    "marcheImmobilier": "accessible",
    "tauxMaisonLabel": "mixte pavillonnaire-collectif"
  },
  {
    "nom": "Labarthe-sur-Lèze",
    "slug": "labarthe-sur-leze",
    "codeInsee": "31248",
    "codePostal": "31860",
    "population": 6585,
    "latitude": 43.4589,
    "longitude": 1.3995,
    "altitude": 156,
    "logements": 2927,
    "logementsMaison": 66,
    "prixM2Moyen": 2200,
    "vehiculesElectriques": 281,
    "croissanceVE": 32,
    "bornesPubliques": 9,
    "intercommunalite": "Communauté de Communes du Volvestre",
    "canton": "Labarthe-sur-Lèze",
    "distanceBordeaux": 16.6,
    "densiteBornes": 1.4,
    "profilCommune": "commune résidentielle",
    "marcheImmobilier": "accessible",
    "tauxMaisonLabel": "majoritairement pavillonnaire"
  },
  {
    "nom": "Eaunes",
    "slug": "eaunes",
    "codeInsee": "31165",
    "codePostal": "31600",
    "population": 6539,
    "latitude": 43.4324,
    "longitude": 1.3543,
    "altitude": 158,
    "logements": 2906,
    "logementsMaison": 68,
    "prixM2Moyen": 2220,
    "vehiculesElectriques": 279,
    "croissanceVE": 23,
    "bornesPubliques": 11,
    "intercommunalite": "Le Muretain Agglo",
    "canton": "Muret",
    "distanceBordeaux": 20.5,
    "densiteBornes": 1.7,
    "profilCommune": "commune résidentielle",
    "marcheImmobilier": "accessible",
    "tauxMaisonLabel": "majoritairement pavillonnaire"
  },
  {
    "nom": "Saint-Alban",
    "slug": "saint-alban",
    "codeInsee": "31467",
    "codePostal": "31140",
    "population": 6534,
    "latitude": 43.6955,
    "longitude": 1.4133,
    "altitude": 135,
    "logements": 2904,
    "logementsMaison": 60,
    "prixM2Moyen": 2350,
    "vehiculesElectriques": 292,
    "croissanceVE": 21,
    "bornesPubliques": 12,
    "intercommunalite": "Toulouse Métropole",
    "canton": "Saint-Alban",
    "distanceBordeaux": 10.4,
    "densiteBornes": 1.8,
    "profilCommune": "commune résidentielle",
    "marcheImmobilier": "accessible",
    "tauxMaisonLabel": "majoritairement pavillonnaire"
  },
  {
    "nom": "Villemur-sur-Tarn",
    "slug": "villemur-sur-tarn",
    "codeInsee": "31584",
    "codePostal": "31340",
    "population": 6345,
    "latitude": 43.8582,
    "longitude": 1.4947,
    "altitude": 132,
    "logements": 2820,
    "logementsMaison": 57,
    "prixM2Moyen": 2470,
    "vehiculesElectriques": 266,
    "croissanceVE": 23,
    "bornesPubliques": 10,
    "intercommunalite": "Communauté de Communes du Volvestre",
    "canton": "Villemur-sur-Tarn",
    "distanceBordeaux": 28.5,
    "densiteBornes": 1.6,
    "profilCommune": "commune résidentielle",
    "marcheImmobilier": "accessible",
    "tauxMaisonLabel": "mixte pavillonnaire-collectif"
  },
  {
    "nom": "Bruguières",
    "slug": "bruguieres",
    "codeInsee": "31091",
    "codePostal": "31150",
    "population": 6202,
    "latitude": 43.7258,
    "longitude": 1.4105,
    "altitude": 130,
    "logements": 2756,
    "logementsMaison": 55,
    "prixM2Moyen": 2570,
    "vehiculesElectriques": 280,
    "croissanceVE": 28,
    "bornesPubliques": 10,
    "intercommunalite": "Toulouse Métropole",
    "canton": "Bruguières",
    "distanceBordeaux": 13.7,
    "densiteBornes": 1.6,
    "profilCommune": "commune résidentielle",
    "marcheImmobilier": "intermédiaire",
    "tauxMaisonLabel": "mixte pavillonnaire-collectif"
  },
  {
    "nom": "Quint-Fonsegrives",
    "slug": "quint-fonsegrives",
    "codeInsee": "31445",
    "codePostal": "31130",
    "population": 6133,
    "latitude": 43.5806,
    "longitude": 1.5372,
    "altitude": 140,
    "logements": 2726,
    "logementsMaison": 65,
    "prixM2Moyen": 2080,
    "vehiculesElectriques": 271,
    "croissanceVE": 29,
    "bornesPubliques": 8,
    "intercommunalite": "Toulouse Métropole",
    "canton": "Quint-Fonsegrives",
    "distanceBordeaux": 8,
    "densiteBornes": 1.3,
    "profilCommune": "commune résidentielle",
    "marcheImmobilier": "accessible",
    "tauxMaisonLabel": "majoritairement pavillonnaire"
  },
  {
    "nom": "Mondonville",
    "slug": "mondonville",
    "codeInsee": "31351",
    "codePostal": "31700",
    "population": 6060,
    "latitude": 43.6691,
    "longitude": 1.2735,
    "altitude": 156,
    "logements": 2693,
    "logementsMaison": 66,
    "prixM2Moyen": 2130,
    "vehiculesElectriques": 254,
    "croissanceVE": 30,
    "bornesPubliques": 10,
    "intercommunalite": "Toulouse Métropole",
    "canton": "Blagnac",
    "distanceBordeaux": 15.5,
    "densiteBornes": 1.7,
    "profilCommune": "commune résidentielle",
    "marcheImmobilier": "accessible",
    "tauxMaisonLabel": "majoritairement pavillonnaire"
  },
  {
    "nom": "Fontenilles",
    "slug": "fontenilles",
    "codeInsee": "31188",
    "codePostal": "31470",
    "population": 5906,
    "latitude": 43.5524,
    "longitude": 1.2048,
    "altitude": 152,
    "logements": 2625,
    "logementsMaison": 62,
    "prixM2Moyen": 2460,
    "vehiculesElectriques": 251,
    "croissanceVE": 23,
    "bornesPubliques": 7,
    "intercommunalite": "Le Muretain Agglo",
    "canton": "Fontenilles",
    "distanceBordeaux": 20.1,
    "densiteBornes": 1.2,
    "profilCommune": "commune résidentielle",
    "marcheImmobilier": "accessible",
    "tauxMaisonLabel": "majoritairement pavillonnaire"
  },
  {
    "nom": "Fenouillet",
    "slug": "fenouillet",
    "codeInsee": "31182",
    "codePostal": "31150",
    "population": 5784,
    "latitude": 43.6864,
    "longitude": 1.3897,
    "altitude": 130,
    "logements": 2571,
    "logementsMaison": 55,
    "prixM2Moyen": 2060,
    "vehiculesElectriques": 222,
    "croissanceVE": 28,
    "bornesPubliques": 11,
    "intercommunalite": "Toulouse Métropole",
    "canton": "Fenouillet",
    "distanceBordeaux": 10.1,
    "densiteBornes": 1.9,
    "profilCommune": "commune résidentielle",
    "marcheImmobilier": "accessible",
    "tauxMaisonLabel": "mixte pavillonnaire-collectif"
  },
  {
    "nom": "Carbonne",
    "slug": "carbonne",
    "codeInsee": "31107",
    "codePostal": "31390",
    "population": 5563,
    "latitude": 43.3063,
    "longitude": 1.2321,
    "altitude": 180,
    "logements": 2472,
    "logementsMaison": 55,
    "prixM2Moyen": 2180,
    "vehiculesElectriques": 224,
    "croissanceVE": 22,
    "bornesPubliques": 10,
    "intercommunalite": "Communauté de Communes Cœur de Garonne",
    "canton": "Carbonne",
    "distanceBordeaux": 37.3,
    "densiteBornes": 1.8,
    "profilCommune": "commune résidentielle",
    "marcheImmobilier": "accessible",
    "tauxMaisonLabel": "mixte pavillonnaire-collectif"
  },
  {
    "nom": "Roques",
    "slug": "roques",
    "codeInsee": "31458",
    "codePostal": "31120",
    "population": 5436,
    "latitude": 43.507,
    "longitude": 1.3576,
    "altitude": 158,
    "logements": 2416,
    "logementsMaison": 68,
    "prixM2Moyen": 2400,
    "vehiculesElectriques": 250,
    "croissanceVE": 23,
    "bornesPubliques": 10,
    "intercommunalite": "Le Muretain Agglo",
    "canton": "Roques",
    "distanceBordeaux": 12.9,
    "densiteBornes": 1.8,
    "profilCommune": "commune résidentielle",
    "marcheImmobilier": "accessible",
    "tauxMaisonLabel": "majoritairement pavillonnaire"
  },
  {
    "nom": "Villefranche-de-Lauragais",
    "slug": "villefranche-de-lauragais",
    "codeInsee": "31582",
    "codePostal": "31290",
    "population": 5072,
    "latitude": 43.4065,
    "longitude": 1.7185,
    "altitude": 165,
    "logements": 2254,
    "logementsMaison": 90,
    "prixM2Moyen": 2530,
    "vehiculesElectriques": 241,
    "croissanceVE": 26,
    "bornesPubliques": 10,
    "intercommunalite": "Communauté de Communes Terres du Lauragais",
    "canton": "Villefranche-de-Lauragais",
    "distanceBordeaux": 31.2,
    "densiteBornes": 2,
    "profilCommune": "commune résidentielle",
    "marcheImmobilier": "intermédiaire",
    "tauxMaisonLabel": "très pavillonnaire"
  },
  {
    "nom": "Pechbonnieu",
    "slug": "pechbonnieu",
    "codeInsee": "31410",
    "codePostal": "31140",
    "population": 4922,
    "latitude": 43.7111,
    "longitude": 1.4561,
    "altitude": 147,
    "logements": 2188,
    "logementsMaison": 57,
    "prixM2Moyen": 2210,
    "vehiculesElectriques": 187,
    "croissanceVE": 24,
    "bornesPubliques": 9,
    "intercommunalite": "Toulouse Métropole",
    "canton": "Pechbonnieu",
    "distanceBordeaux": 11.9,
    "densiteBornes": 1.8,
    "profilCommune": "commune résidentielle",
    "marcheImmobilier": "accessible",
    "tauxMaisonLabel": "mixte pavillonnaire-collectif"
  },
  {
    "nom": "Gratentour",
    "slug": "gratentour",
    "codeInsee": "31230",
    "codePostal": "31150",
    "population": 4906,
    "latitude": 43.7206,
    "longitude": 1.4333,
    "altitude": 156,
    "logements": 2180,
    "logementsMaison": 66,
    "prixM2Moyen": 2440,
    "vehiculesElectriques": 181,
    "croissanceVE": 23,
    "bornesPubliques": 11,
    "intercommunalite": "Toulouse Métropole",
    "canton": "Gratentour",
    "distanceBordeaux": 12.9,
    "densiteBornes": 2.2,
    "profilCommune": "commune résidentielle",
    "marcheImmobilier": "accessible",
    "tauxMaisonLabel": "majoritairement pavillonnaire"
  },
  {
    "nom": "Cazères",
    "slug": "cazeres",
    "codeInsee": "31135",
    "codePostal": "31220",
    "population": 4854,
    "latitude": 43.2155,
    "longitude": 1.1005,
    "altitude": 260,
    "logements": 2157,
    "logementsMaison": 60,
    "prixM2Moyen": 2340,
    "vehiculesElectriques": 188,
    "croissanceVE": 22,
    "bornesPubliques": 8,
    "intercommunalite": "Communauté de Communes Cœur de Garonne",
    "canton": "Cazères",
    "distanceBordeaux": 51.4,
    "densiteBornes": 1.6,
    "profilCommune": "commune résidentielle",
    "marcheImmobilier": "accessible",
    "tauxMaisonLabel": "majoritairement pavillonnaire"
  },
  {
    "nom": "Auzeville-Tolosane",
    "slug": "auzeville-tolosane",
    "codeInsee": "31035",
    "codePostal": "31320",
    "population": 4665,
    "latitude": 43.5285,
    "longitude": 1.4896,
    "altitude": 148,
    "logements": 2073,
    "logementsMaison": 58,
    "prixM2Moyen": 2250,
    "vehiculesElectriques": 200,
    "croissanceVE": 21,
    "bornesPubliques": 7,
    "intercommunalite": "Communauté de Communes du SICOVAL",
    "canton": "Auzeville-Tolosane",
    "distanceBordeaux": 9.2,
    "densiteBornes": 1.5,
    "profilCommune": "commune résidentielle",
    "marcheImmobilier": "accessible",
    "tauxMaisonLabel": "mixte pavillonnaire-collectif"
  },
  {
    "nom": "Bouloc",
    "slug": "bouloc",
    "codeInsee": "31079",
    "codePostal": "31620",
    "population": 4618,
    "latitude": 43.7958,
    "longitude": 1.4192,
    "altitude": 155,
    "logements": 2052,
    "logementsMaison": 65,
    "prixM2Moyen": 2010,
    "vehiculesElectriques": 163,
    "croissanceVE": 26,
    "bornesPubliques": 6,
    "intercommunalite": "Communauté de Communes du Frontonnais",
    "canton": "Bouloc",
    "distanceBordeaux": 21.3,
    "densiteBornes": 1.3,
    "profilCommune": "commune résidentielle",
    "marcheImmobilier": "accessible",
    "tauxMaisonLabel": "majoritairement pavillonnaire"
  },
  {
    "nom": "Castelmaurou",
    "slug": "castelmaurou",
    "codeInsee": "31117",
    "codePostal": "31180",
    "population": 4524,
    "latitude": 43.6863,
    "longitude": 1.5289,
    "altitude": 154,
    "logements": 2011,
    "logementsMaison": 64,
    "prixM2Moyen": 2410,
    "vehiculesElectriques": 172,
    "croissanceVE": 31,
    "bornesPubliques": 7,
    "intercommunalite": "Communauté de Communes du Volvestre",
    "canton": "Castelmaurou",
    "distanceBordeaux": 11.4,
    "densiteBornes": 1.5,
    "profilCommune": "commune résidentielle",
    "marcheImmobilier": "accessible",
    "tauxMaisonLabel": "majoritairement pavillonnaire"
  },
  {
    "nom": "Montrabé",
    "slug": "montrabe",
    "codeInsee": "31389",
    "codePostal": "31850",
    "population": 4473,
    "latitude": 43.6436,
    "longitude": 1.5333,
    "altitude": 151,
    "logements": 1988,
    "logementsMaison": 61,
    "prixM2Moyen": 2470,
    "vehiculesElectriques": 179,
    "croissanceVE": 24,
    "bornesPubliques": 10,
    "intercommunalite": "Communauté de Communes du Volvestre",
    "canton": "Montrabé",
    "distanceBordeaux": 8.4,
    "densiteBornes": 2.2,
    "profilCommune": "commune résidentielle",
    "marcheImmobilier": "accessible",
    "tauxMaisonLabel": "majoritairement pavillonnaire"
  },
  {
    "nom": "Labège",
    "slug": "labege",
    "codeInsee": "31254",
    "codePostal": "31670",
    "population": 4392,
    "latitude": 43.5396,
    "longitude": 1.5207,
    "altitude": 131,
    "logements": 1952,
    "logementsMaison": 56,
    "prixM2Moyen": 2200,
    "vehiculesElectriques": 174,
    "croissanceVE": 20,
    "bornesPubliques": 7,
    "intercommunalite": "Communauté de Communes du SICOVAL",
    "canton": "Labège",
    "distanceBordeaux": 9.5,
    "densiteBornes": 1.6,
    "profilCommune": "commune résidentielle",
    "marcheImmobilier": "accessible",
    "tauxMaisonLabel": "mixte pavillonnaire-collectif"
  },
  {
    "nom": "Pins-Justaret",
    "slug": "pins-justaret",
    "codeInsee": "31421",
    "codePostal": "31860",
    "population": 4378,
    "latitude": 43.4825,
    "longitude": 1.3914,
    "altitude": 156,
    "logements": 1946,
    "logementsMaison": 66,
    "prixM2Moyen": 2030,
    "vehiculesElectriques": 171,
    "croissanceVE": 21,
    "bornesPubliques": 7,
    "intercommunalite": "Le Muretain Agglo",
    "canton": "Pins-Justaret",
    "distanceBordeaux": 14.2,
    "densiteBornes": 1.6,
    "profilCommune": "commune résidentielle",
    "marcheImmobilier": "accessible",
    "tauxMaisonLabel": "majoritairement pavillonnaire"
  },
  {
    "nom": "Bessières",
    "slug": "bessieres",
    "codeInsee": "31066",
    "codePostal": "31660",
    "population": 4310,
    "latitude": 43.794,
    "longitude": 1.5846,
    "altitude": 138,
    "logements": 1916,
    "logementsMaison": 63,
    "prixM2Moyen": 2590,
    "vehiculesElectriques": 181,
    "croissanceVE": 34,
    "bornesPubliques": 6,
    "intercommunalite": "Communauté de Communes du Volvestre",
    "canton": "Bessières",
    "distanceBordeaux": 23.9,
    "densiteBornes": 1.4,
    "profilCommune": "commune résidentielle",
    "marcheImmobilier": "intermédiaire",
    "tauxMaisonLabel": "majoritairement pavillonnaire"
  },
  {
    "nom": "Roquettes",
    "slug": "roquettes",
    "codeInsee": "31460",
    "codePostal": "31120",
    "population": 4280,
    "latitude": 43.4948,
    "longitude": 1.3745,
    "altitude": 131,
    "logements": 1902,
    "logementsMaison": 56,
    "prixM2Moyen": 2120,
    "vehiculesElectriques": 168,
    "croissanceVE": 27,
    "bornesPubliques": 8,
    "intercommunalite": "Le Muretain Agglo",
    "canton": "Roquettes",
    "distanceBordeaux": 13.4,
    "densiteBornes": 1.9,
    "profilCommune": "commune résidentielle",
    "marcheImmobilier": "accessible",
    "tauxMaisonLabel": "mixte pavillonnaire-collectif"
  },
  {
    "nom": "Nailloux",
    "slug": "nailloux",
    "codeInsee": "31396",
    "codePostal": "31560",
    "population": 4211,
    "latitude": 43.3673,
    "longitude": 1.6115,
    "altitude": 251,
    "logements": 1872,
    "logementsMaison": 91,
    "prixM2Moyen": 2140,
    "vehiculesElectriques": 197,
    "croissanceVE": 33,
    "bornesPubliques": 9,
    "intercommunalite": "Communauté de Communes du Volvestre",
    "canton": "Nailloux",
    "distanceBordeaux": 29.6,
    "densiteBornes": 2.1,
    "profilCommune": "commune résidentielle",
    "marcheImmobilier": "accessible",
    "tauxMaisonLabel": "très pavillonnaire"
  },
  {
    "nom": "Verfeil",
    "slug": "verfeil",
    "codeInsee": "31573",
    "codePostal": "31590",
    "population": 3954,
    "latitude": 43.6579,
    "longitude": 1.6792,
    "altitude": 226,
    "logements": 1757,
    "logementsMaison": 92,
    "prixM2Moyen": 2540,
    "vehiculesElectriques": 193,
    "croissanceVE": 22,
    "bornesPubliques": 6,
    "intercommunalite": "Communauté de Communes du Volvestre",
    "canton": "Verfeil",
    "distanceBordeaux": 19.8,
    "densiteBornes": 1.5,
    "profilCommune": "bourg périurbain",
    "marcheImmobilier": "intermédiaire",
    "tauxMaisonLabel": "très pavillonnaire"
  },
  {
    "nom": "Lherm",
    "slug": "lherm",
    "codeInsee": "31299",
    "codePostal": "31600",
    "population": 3880,
    "latitude": 43.4273,
    "longitude": 1.2288,
    "altitude": 147,
    "logements": 1724,
    "logementsMaison": 57,
    "prixM2Moyen": 2400,
    "vehiculesElectriques": 134,
    "croissanceVE": 20,
    "bornesPubliques": 7,
    "intercommunalite": "Le Muretain Agglo",
    "canton": "Muret",
    "distanceBordeaux": 26.3,
    "densiteBornes": 1.8,
    "profilCommune": "bourg périurbain",
    "marcheImmobilier": "accessible",
    "tauxMaisonLabel": "mixte pavillonnaire-collectif"
  },
  {
    "nom": "Lavernose-Lacasse",
    "slug": "lavernose-lacasse",
    "codeInsee": "31287",
    "codePostal": "31410",
    "population": 3798,
    "latitude": 43.391,
    "longitude": 1.2411,
    "altitude": 241,
    "logements": 1688,
    "logementsMaison": 56,
    "prixM2Moyen": 2530,
    "vehiculesElectriques": 161,
    "croissanceVE": 22,
    "bornesPubliques": 10,
    "intercommunalite": "Communauté de Communes du Volvestre",
    "canton": "Lavernose-Lacasse",
    "distanceBordeaux": 28.9,
    "densiteBornes": 2.6,
    "profilCommune": "bourg périurbain",
    "marcheImmobilier": "intermédiaire",
    "tauxMaisonLabel": "mixte pavillonnaire-collectif"
  },
  {
    "nom": "Montastruc-la-Conseillère",
    "slug": "montastruc-la-conseillere",
    "codeInsee": "31358",
    "codePostal": "31380",
    "population": 3708,
    "latitude": 43.7209,
    "longitude": 1.5899,
    "altitude": 155,
    "logements": 1648,
    "logementsMaison": 65,
    "prixM2Moyen": 2450,
    "vehiculesElectriques": 138,
    "croissanceVE": 26,
    "bornesPubliques": 7,
    "intercommunalite": "Communauté de Communes du Volvestre",
    "canton": "Montastruc-la-Conseillère",
    "distanceBordeaux": 17.4,
    "densiteBornes": 1.9,
    "profilCommune": "bourg périurbain",
    "marcheImmobilier": "accessible",
    "tauxMaisonLabel": "majoritairement pavillonnaire"
  },
  {
    "nom": "Baziège",
    "slug": "baziege",
    "codeInsee": "31048",
    "codePostal": "31450",
    "population": 3583,
    "latitude": 43.4614,
    "longitude": 1.6294,
    "altitude": 212,
    "logements": 1592,
    "logementsMaison": 86,
    "prixM2Moyen": 2380,
    "vehiculesElectriques": 178,
    "croissanceVE": 25,
    "bornesPubliques": 9,
    "intercommunalite": "Communauté de Communes du Volvestre",
    "canton": "Baziège",
    "distanceBordeaux": 21.8,
    "densiteBornes": 2.5,
    "profilCommune": "bourg périurbain",
    "marcheImmobilier": "accessible",
    "tauxMaisonLabel": "très pavillonnaire"
  },
  {
    "nom": "Rieumes",
    "slug": "rieumes",
    "codeInsee": "31454",
    "codePostal": "31370",
    "population": 3517,
    "latitude": 43.413,
    "longitude": 1.1104,
    "altitude": 145,
    "logements": 1563,
    "logementsMaison": 55,
    "prixM2Moyen": 2310,
    "vehiculesElectriques": 142,
    "croissanceVE": 32,
    "bornesPubliques": 7,
    "intercommunalite": "Communauté de Communes du Volvestre",
    "canton": "Rieumes",
    "distanceBordeaux": 34.3,
    "densiteBornes": 2,
    "profilCommune": "bourg périurbain",
    "marcheImmobilier": "accessible",
    "tauxMaisonLabel": "mixte pavillonnaire-collectif"
  },
  {
    "nom": "Longages",
    "slug": "longages",
    "codeInsee": "31303",
    "codePostal": "31410",
    "population": 3392,
    "latitude": 43.3571,
    "longitude": 1.2114,
    "altitude": 263,
    "logements": 1508,
    "logementsMaison": 63,
    "prixM2Moyen": 2010,
    "vehiculesElectriques": 144,
    "croissanceVE": 26,
    "bornesPubliques": 7,
    "intercommunalite": "Communauté de Communes du Volvestre",
    "canton": "Longages",
    "distanceBordeaux": 33.3,
    "densiteBornes": 2.1,
    "profilCommune": "bourg périurbain",
    "marcheImmobilier": "accessible",
    "tauxMaisonLabel": "majoritairement pavillonnaire"
  },
  {
    "nom": "Vernet",
    "slug": "vernet",
    "codeInsee": "31574",
    "codePostal": "31810",
    "population": 3381,
    "latitude": 43.4272,
    "longitude": 1.4193,
    "altitude": 139,
    "logements": 1503,
    "logementsMaison": 64,
    "prixM2Moyen": 2460,
    "vehiculesElectriques": 140,
    "croissanceVE": 27,
    "bornesPubliques": 10,
    "intercommunalite": "Communauté de Communes du Volvestre",
    "canton": "Vernet",
    "distanceBordeaux": 19.8,
    "densiteBornes": 3,
    "profilCommune": "bourg périurbain",
    "marcheImmobilier": "accessible",
    "tauxMaisonLabel": "majoritairement pavillonnaire"
  },
  {
    "nom": "Seilh",
    "slug": "seilh",
    "codeInsee": "31541",
    "codePostal": "31840",
    "population": 3356,
    "latitude": 43.692,
    "longitude": 1.3574,
    "altitude": 144,
    "logements": 1492,
    "logementsMaison": 69,
    "prixM2Moyen": 2130,
    "vehiculesElectriques": 153,
    "croissanceVE": 23,
    "bornesPubliques": 8,
    "intercommunalite": "Toulouse Métropole",
    "canton": "Seilh",
    "distanceBordeaux": 12,
    "densiteBornes": 2.4,
    "profilCommune": "bourg périurbain",
    "marcheImmobilier": "accessible",
    "tauxMaisonLabel": "majoritairement pavillonnaire"
  },
  {
    "nom": "Lagardelle-sur-Lèze",
    "slug": "lagardelle-sur-leze",
    "codeInsee": "31263",
    "codePostal": "31870",
    "population": 3303,
    "latitude": 43.4162,
    "longitude": 1.3929,
    "altitude": 134,
    "logements": 1468,
    "logementsMaison": 59,
    "prixM2Moyen": 2580,
    "vehiculesElectriques": 147,
    "croissanceVE": 23,
    "bornesPubliques": 5,
    "intercommunalite": "Communauté de Communes du Volvestre",
    "canton": "Lagardelle-sur-Lèze",
    "distanceBordeaux": 21.4,
    "densiteBornes": 1.5,
    "profilCommune": "bourg périurbain",
    "marcheImmobilier": "intermédiaire",
    "tauxMaisonLabel": "mixte pavillonnaire-collectif"
  },
  {
    "nom": "Lespinasse",
    "slug": "lespinasse",
    "codeInsee": "31293",
    "codePostal": "31150",
    "population": 3251,
    "latitude": 43.7174,
    "longitude": 1.3821,
    "altitude": 152,
    "logements": 1445,
    "logementsMaison": 62,
    "prixM2Moyen": 2230,
    "vehiculesElectriques": 127,
    "croissanceVE": 20,
    "bornesPubliques": 9,
    "intercommunalite": "Toulouse Métropole",
    "canton": "Lespinasse",
    "distanceBordeaux": 13.5,
    "densiteBornes": 2.8,
    "profilCommune": "bourg périurbain",
    "marcheImmobilier": "accessible",
    "tauxMaisonLabel": "majoritairement pavillonnaire"
  },
  {
    "nom": "Fonbeauzard",
    "slug": "fonbeauzard",
    "codeInsee": "31186",
    "codePostal": "31140",
    "population": 3204,
    "latitude": 43.6792,
    "longitude": 1.4368,
    "altitude": 146,
    "logements": 1424,
    "logementsMaison": 56,
    "prixM2Moyen": 2120,
    "vehiculesElectriques": 107,
    "croissanceVE": 25,
    "bornesPubliques": 8,
    "intercommunalite": "Toulouse Métropole",
    "canton": "Fonbeauzard",
    "distanceBordeaux": 8.3,
    "densiteBornes": 2.5,
    "profilCommune": "bourg périurbain",
    "marcheImmobilier": "accessible",
    "tauxMaisonLabel": "mixte pavillonnaire-collectif"
  },
  {
    "nom": "Gagnac-sur-Garonne",
    "slug": "gagnac-sur-garonne",
    "codeInsee": "31205",
    "codePostal": "31150",
    "population": 3198,
    "latitude": 43.7077,
    "longitude": 1.3636,
    "altitude": 136,
    "logements": 1421,
    "logementsMaison": 61,
    "prixM2Moyen": 2490,
    "vehiculesElectriques": 143,
    "croissanceVE": 26,
    "bornesPubliques": 6,
    "intercommunalite": "Toulouse Métropole",
    "canton": "Gagnac-sur-Garonne",
    "distanceBordeaux": 13.2,
    "densiteBornes": 1.9,
    "profilCommune": "bourg périurbain",
    "marcheImmobilier": "accessible",
    "tauxMaisonLabel": "majoritairement pavillonnaire"
  },
  {
    "nom": "Montberon",
    "slug": "montberon",
    "codeInsee": "31364",
    "codePostal": "31140",
    "population": 3158,
    "latitude": 43.7188,
    "longitude": 1.4901,
    "altitude": 135,
    "logements": 1404,
    "logementsMaison": 60,
    "prixM2Moyen": 2470,
    "vehiculesElectriques": 132,
    "croissanceVE": 34,
    "bornesPubliques": 8,
    "intercommunalite": "Toulouse Métropole",
    "canton": "Montberon",
    "distanceBordeaux": 13.2,
    "densiteBornes": 2.5,
    "profilCommune": "bourg périurbain",
    "marcheImmobilier": "accessible",
    "tauxMaisonLabel": "majoritairement pavillonnaire"
  },
  {
    "nom": "Bérat",
    "slug": "berat",
    "codeInsee": "31065",
    "codePostal": "31370",
    "population": 3087,
    "latitude": 43.3771,
    "longitude": 1.1742,
    "altitude": 247,
    "logements": 1372,
    "logementsMaison": 62,
    "prixM2Moyen": 2390,
    "vehiculesElectriques": 123,
    "croissanceVE": 30,
    "bornesPubliques": 6,
    "intercommunalite": "Communauté de Communes du Volvestre",
    "canton": "Bérat",
    "distanceBordeaux": 33.4,
    "densiteBornes": 1.9,
    "profilCommune": "bourg périurbain",
    "marcheImmobilier": "accessible",
    "tauxMaisonLabel": "majoritairement pavillonnaire"
  },
  {
    "nom": "Noé",
    "slug": "noe",
    "codeInsee": "31399",
    "codePostal": "31410",
    "population": 3067,
    "latitude": 43.3644,
    "longitude": 1.2704,
    "altitude": 269,
    "logements": 1363,
    "logementsMaison": 69,
    "prixM2Moyen": 2090,
    "vehiculesElectriques": 119,
    "croissanceVE": 25,
    "bornesPubliques": 6,
    "intercommunalite": "Communauté de Communes du Volvestre",
    "canton": "Noé",
    "distanceBordeaux": 30.2,
    "densiteBornes": 2,
    "profilCommune": "bourg périurbain",
    "marcheImmobilier": "accessible",
    "tauxMaisonLabel": "majoritairement pavillonnaire"
  },
  {
    "nom": "Montesquieu-Volvestre",
    "slug": "montesquieu-volvestre",
    "codeInsee": "31375",
    "codePostal": "31310",
    "population": 3050,
    "latitude": 43.1778,
    "longitude": 1.2184,
    "altitude": 391,
    "logements": 1356,
    "logementsMaison": 89,
    "prixM2Moyen": 2020,
    "vehiculesElectriques": 143,
    "croissanceVE": 25,
    "bornesPubliques": 6,
    "intercommunalite": "Communauté de Communes du Volvestre",
    "canton": "Montesquieu-Volvestre",
    "distanceBordeaux": 50.9,
    "densiteBornes": 2,
    "profilCommune": "bourg périurbain",
    "marcheImmobilier": "accessible",
    "tauxMaisonLabel": "très pavillonnaire"
  },
  {
    "nom": "Lapeyrouse-Fossat",
    "slug": "lapeyrouse-fossat",
    "codeInsee": "31273",
    "codePostal": "31180",
    "population": 3043,
    "latitude": 43.7033,
    "longitude": 1.5103,
    "altitude": 141,
    "logements": 1352,
    "logementsMaison": 66,
    "prixM2Moyen": 2580,
    "vehiculesElectriques": 124,
    "croissanceVE": 26,
    "bornesPubliques": 5,
    "intercommunalite": "Communauté de Communes du Volvestre",
    "canton": "Lapeyrouse-Fossat",
    "distanceBordeaux": 12.2,
    "densiteBornes": 1.6,
    "profilCommune": "bourg périurbain",
    "marcheImmobilier": "intermédiaire",
    "tauxMaisonLabel": "majoritairement pavillonnaire"
  },
  {
    "nom": "Brax",
    "slug": "brax",
    "codeInsee": "31088",
    "codePostal": "31490",
    "population": 3037,
    "latitude": 43.6154,
    "longitude": 1.2309,
    "altitude": 146,
    "logements": 1350,
    "logementsMaison": 56,
    "prixM2Moyen": 2280,
    "vehiculesElectriques": 123,
    "croissanceVE": 27,
    "bornesPubliques": 8,
    "intercommunalite": "Toulouse Métropole",
    "canton": "Brax",
    "distanceBordeaux": 17.2,
    "densiteBornes": 2.6,
    "profilCommune": "bourg périurbain",
    "marcheImmobilier": "accessible",
    "tauxMaisonLabel": "mixte pavillonnaire-collectif"
  },
  {
    "nom": "Cintegabelle",
    "slug": "cintegabelle",
    "codeInsee": "31145",
    "codePostal": "31550",
    "population": 3006,
    "latitude": 43.3,
    "longitude": 1.5375,
    "altitude": 262,
    "logements": 1336,
    "logementsMaison": 62,
    "prixM2Moyen": 2020,
    "vehiculesElectriques": 121,
    "croissanceVE": 31,
    "bornesPubliques": 9,
    "intercommunalite": "Communauté de Communes du Volvestre",
    "canton": "Cintegabelle",
    "distanceBordeaux": 34.7,
    "densiteBornes": 3,
    "profilCommune": "bourg périurbain",
    "marcheImmobilier": "accessible",
    "tauxMaisonLabel": "majoritairement pavillonnaire"
  },
  {
    "nom": "Venerque",
    "slug": "venerque",
    "codeInsee": "31572",
    "codePostal": "31810",
    "population": 2974,
    "latitude": 43.4363,
    "longitude": 1.4629,
    "altitude": 148,
    "logements": 1322,
    "logementsMaison": 58,
    "prixM2Moyen": 2170,
    "vehiculesElectriques": 100,
    "croissanceVE": 31,
    "bornesPubliques": 5,
    "intercommunalite": "Communauté de Communes du Volvestre",
    "canton": "Venerque",
    "distanceBordeaux": 18.8,
    "densiteBornes": 1.7,
    "profilCommune": "bourg périurbain",
    "marcheImmobilier": "accessible",
    "tauxMaisonLabel": "mixte pavillonnaire-collectif"
  },
  {
    "nom": "Buzet-sur-Tarn",
    "slug": "buzet-sur-tarn",
    "codeInsee": "31094",
    "codePostal": "31660",
    "population": 2963,
    "latitude": 43.7721,
    "longitude": 1.6099,
    "altitude": 236,
    "logements": 1317,
    "logementsMaison": 88,
    "prixM2Moyen": 2100,
    "vehiculesElectriques": 119,
    "croissanceVE": 23,
    "bornesPubliques": 6,
    "intercommunalite": "Communauté de Communes du Volvestre",
    "canton": "Buzet-sur-Tarn",
    "distanceBordeaux": 22.9,
    "densiteBornes": 2,
    "profilCommune": "bourg périurbain",
    "marcheImmobilier": "accessible",
    "tauxMaisonLabel": "très pavillonnaire"
  },
  {
    "nom": "Labastidette",
    "slug": "labastidette",
    "codeInsee": "31253",
    "codePostal": "31600",
    "population": 2930,
    "latitude": 43.4554,
    "longitude": 1.2411,
    "altitude": 155,
    "logements": 1302,
    "logementsMaison": 65,
    "prixM2Moyen": 2270,
    "vehiculesElectriques": 130,
    "croissanceVE": 26,
    "bornesPubliques": 6,
    "intercommunalite": "Le Muretain Agglo",
    "canton": "Muret",
    "distanceBordeaux": 23.3,
    "densiteBornes": 2,
    "profilCommune": "bourg périurbain",
    "marcheImmobilier": "accessible",
    "tauxMaisonLabel": "majoritairement pavillonnaire"
  },
  {
    "nom": "Miremont",
    "slug": "miremont",
    "codeInsee": "31345",
    "codePostal": "31190",
    "population": 2838,
    "latitude": 43.3733,
    "longitude": 1.4177,
    "altitude": 240,
    "logements": 1261,
    "logementsMaison": 55,
    "prixM2Moyen": 2360,
    "vehiculesElectriques": 100,
    "croissanceVE": 34,
    "bornesPubliques": 9,
    "intercommunalite": "Communauté de Communes du Bassin Auterivain",
    "canton": "Miremont",
    "distanceBordeaux": 25.8,
    "densiteBornes": 3.2,
    "profilCommune": "bourg périurbain",
    "marcheImmobilier": "accessible",
    "tauxMaisonLabel": "mixte pavillonnaire-collectif"
  },
  {
    "nom": "Ayguesvives",
    "slug": "ayguesvives",
    "codeInsee": "31004",
    "codePostal": "31450",
    "population": 2812,
    "latitude": 43.4236,
    "longitude": 1.5965,
    "altitude": 158,
    "logements": 1250,
    "logementsMaison": 68,
    "prixM2Moyen": 2460,
    "vehiculesElectriques": 115,
    "croissanceVE": 32,
    "bornesPubliques": 9,
    "intercommunalite": "Communauté de Communes du Volvestre",
    "canton": "Ayguesvives",
    "distanceBordeaux": 23.6,
    "densiteBornes": 3.2,
    "profilCommune": "bourg périurbain",
    "marcheImmobilier": "accessible",
    "tauxMaisonLabel": "majoritairement pavillonnaire"
  },
  {
    "nom": "Pinsaguel",
    "slug": "pinsaguel",
    "codeInsee": "31420",
    "codePostal": "31120",
    "population": 2786,
    "latitude": 43.503,
    "longitude": 1.3919,
    "altitude": 141,
    "logements": 1238,
    "logementsMaison": 66,
    "prixM2Moyen": 2330,
    "vehiculesElectriques": 106,
    "croissanceVE": 22,
    "bornesPubliques": 7,
    "intercommunalite": "Le Muretain Agglo",
    "canton": "Pinsaguel",
    "distanceBordeaux": 12.1,
    "densiteBornes": 2.5,
    "profilCommune": "bourg périurbain",
    "marcheImmobilier": "accessible",
    "tauxMaisonLabel": "majoritairement pavillonnaire"
  },
  {
    "nom": "Montréjeau",
    "slug": "montrejeau",
    "codeInsee": "31390",
    "codePostal": "31210",
    "population": 2648,
    "latitude": 43.0876,
    "longitude": 0.5588,
    "altitude": 371,
    "logements": 1177,
    "logementsMaison": 85,
    "prixM2Moyen": 2190,
    "vehiculesElectriques": 103,
    "croissanceVE": 28,
    "bornesPubliques": 6,
    "intercommunalite": "Communauté de Communes du Volvestre",
    "canton": "Montréjeau",
    "distanceBordeaux": 91.8,
    "densiteBornes": 2.3,
    "profilCommune": "bourg périurbain",
    "marcheImmobilier": "accessible",
    "tauxMaisonLabel": "très pavillonnaire"
  },
  {
    "nom": "Daux",
    "slug": "daux",
    "codeInsee": "31160",
    "codePostal": "31700",
    "population": 2643,
    "latitude": 43.6849,
    "longitude": 1.2685,
    "altitude": 151,
    "logements": 1175,
    "logementsMaison": 61,
    "prixM2Moyen": 2350,
    "vehiculesElectriques": 98,
    "croissanceVE": 32,
    "bornesPubliques": 8,
    "intercommunalite": "Toulouse Métropole",
    "canton": "Blagnac",
    "distanceBordeaux": 16.7,
    "densiteBornes": 3,
    "profilCommune": "bourg périurbain",
    "marcheImmobilier": "accessible",
    "tauxMaisonLabel": "majoritairement pavillonnaire"
  },
  {
    "nom": "Rieux-Volvestre",
    "slug": "rieux-volvestre",
    "codeInsee": "31455",
    "codePostal": "31310",
    "population": 2639,
    "latitude": 43.2538,
    "longitude": 1.2096,
    "altitude": 253,
    "logements": 1173,
    "logementsMaison": 68,
    "prixM2Moyen": 2170,
    "vehiculesElectriques": 103,
    "croissanceVE": 23,
    "bornesPubliques": 5,
    "intercommunalite": "Communauté de Communes du Volvestre",
    "canton": "Rieux-Volvestre",
    "distanceBordeaux": 43.4,
    "densiteBornes": 1.9,
    "profilCommune": "bourg périurbain",
    "marcheImmobilier": "accessible",
    "tauxMaisonLabel": "majoritairement pavillonnaire"
  },
  {
    "nom": "Drémil-Lafage",
    "slug": "dremil-lafage",
    "codeInsee": "31163",
    "codePostal": "31280",
    "population": 2608,
    "latitude": 43.592,
    "longitude": 1.5996,
    "altitude": 147,
    "logements": 1159,
    "logementsMaison": 57,
    "prixM2Moyen": 2310,
    "vehiculesElectriques": 106,
    "croissanceVE": 33,
    "bornesPubliques": 7,
    "intercommunalite": "Communauté de Communes du Volvestre",
    "canton": "Drémil-Lafage",
    "distanceBordeaux": 12.6,
    "densiteBornes": 2.7,
    "profilCommune": "bourg périurbain",
    "marcheImmobilier": "accessible",
    "tauxMaisonLabel": "mixte pavillonnaire-collectif"
  },
  {
    "nom": "Le Fauga",
    "slug": "le-fauga",
    "codeInsee": "31181",
    "codePostal": "31410",
    "population": 2603,
    "latitude": 43.3996,
    "longitude": 1.3003,
    "altitude": 263,
    "logements": 1157,
    "logementsMaison": 63,
    "prixM2Moyen": 2230,
    "vehiculesElectriques": 111,
    "croissanceVE": 29,
    "bornesPubliques": 9,
    "intercommunalite": "Communauté de Communes du Volvestre",
    "canton": "Le Fauga",
    "distanceBordeaux": 25.6,
    "densiteBornes": 3.5,
    "profilCommune": "bourg périurbain",
    "marcheImmobilier": "accessible",
    "tauxMaisonLabel": "majoritairement pavillonnaire"
  },
  {
    "nom": "Montgiscard",
    "slug": "montgiscard",
    "codeInsee": "31381",
    "codePostal": "31450",
    "population": 2587,
    "latitude": 43.4507,
    "longitude": 1.5687,
    "altitude": 134,
    "logements": 1150,
    "logementsMaison": 59,
    "prixM2Moyen": 2350,
    "vehiculesElectriques": 116,
    "croissanceVE": 22,
    "bornesPubliques": 5,
    "intercommunalite": "Communauté de Communes du Volvestre",
    "canton": "Montgiscard",
    "distanceBordeaux": 19.8,
    "densiteBornes": 1.9,
    "profilCommune": "bourg périurbain",
    "marcheImmobilier": "accessible",
    "tauxMaisonLabel": "mixte pavillonnaire-collectif"
  },
  {
    "nom": "Sainte-Foy-d'Aigrefeuille",
    "slug": "sainte-foy-d-aigrefeuille",
    "codeInsee": "31480",
    "codePostal": "31570",
    "population": 2576,
    "latitude": 43.5514,
    "longitude": 1.6037,
    "altitude": 224,
    "logements": 1145,
    "logementsMaison": 86,
    "prixM2Moyen": 2430,
    "vehiculesElectriques": 128,
    "croissanceVE": 30,
    "bornesPubliques": 7,
    "intercommunalite": "Communauté de Communes du Volvestre",
    "canton": "Sainte-Foy-d'Aigrefeuille",
    "distanceBordeaux": 14.1,
    "densiteBornes": 2.7,
    "profilCommune": "bourg périurbain",
    "marcheImmobilier": "accessible",
    "tauxMaisonLabel": "très pavillonnaire"
  },
  {
    "nom": "Gragnague",
    "slug": "gragnague",
    "codeInsee": "31228",
    "codePostal": "31380",
    "population": 2553,
    "latitude": 43.6852,
    "longitude": 1.5828,
    "altitude": 150,
    "logements": 1135,
    "logementsMaison": 60,
    "prixM2Moyen": 2030,
    "vehiculesElectriques": 90,
    "croissanceVE": 34,
    "bornesPubliques": 8,
    "intercommunalite": "Communauté de Communes du Volvestre",
    "canton": "Gragnague",
    "distanceBordeaux": 14.3,
    "densiteBornes": 3.1,
    "profilCommune": "bourg périurbain",
    "marcheImmobilier": "accessible",
    "tauxMaisonLabel": "majoritairement pavillonnaire"
  },
  {
    "nom": "Caraman",
    "slug": "caraman",
    "codeInsee": "31106",
    "codePostal": "31460",
    "population": 2513,
    "latitude": 43.5324,
    "longitude": 1.7487,
    "altitude": 234,
    "logements": 1117,
    "logementsMaison": 94,
    "prixM2Moyen": 2070,
    "vehiculesElectriques": 118,
    "croissanceVE": 26,
    "bornesPubliques": 7,
    "intercommunalite": "Communauté de Communes Terres du Lauragais",
    "canton": "Caraman",
    "distanceBordeaux": 25.8,
    "densiteBornes": 2.8,
    "profilCommune": "bourg périurbain",
    "marcheImmobilier": "accessible",
    "tauxMaisonLabel": "très pavillonnaire"
  },
  {
    "nom": "Saint-Geniès-Bellevue",
    "slug": "saint-genies-bellevue",
    "codeInsee": "31484",
    "codePostal": "31180",
    "population": 2495,
    "latitude": 43.6809,
    "longitude": 1.4819,
    "altitude": 133,
    "logements": 1109,
    "logementsMaison": 58,
    "prixM2Moyen": 2390,
    "vehiculesElectriques": 105,
    "croissanceVE": 22,
    "bornesPubliques": 9,
    "intercommunalite": "Communauté de Communes du Volvestre",
    "canton": "Saint-Geniès-Bellevue",
    "distanceBordeaux": 9,
    "densiteBornes": 3.6,
    "profilCommune": "bourg périurbain",
    "marcheImmobilier": "accessible",
    "tauxMaisonLabel": "mixte pavillonnaire-collectif"
  },
  {
    "nom": "Calmont",
    "slug": "calmont",
    "codeInsee": "31100",
    "codePostal": "31560",
    "population": 2494,
    "latitude": 43.2832,
    "longitude": 1.6251,
    "altitude": 261,
    "logements": 1108,
    "logementsMaison": 87,
    "prixM2Moyen": 2370,
    "vehiculesElectriques": 116,
    "croissanceVE": 23,
    "bornesPubliques": 5,
    "intercommunalite": "Communauté de Communes du Volvestre",
    "canton": "Calmont",
    "distanceBordeaux": 38.6,
    "densiteBornes": 2,
    "profilCommune": "bourg périurbain",
    "marcheImmobilier": "accessible",
    "tauxMaisonLabel": "très pavillonnaire"
  },
  {
    "nom": "Péchabou",
    "slug": "pechabou",
    "codeInsee": "31409",
    "codePostal": "31320",
    "population": 2449,
    "latitude": 43.5012,
    "longitude": 1.5124,
    "altitude": 140,
    "logements": 1088,
    "logementsMaison": 65,
    "prixM2Moyen": 2180,
    "vehiculesElectriques": 108,
    "croissanceVE": 27,
    "bornesPubliques": 8,
    "intercommunalite": "Communauté de Communes du SICOVAL",
    "canton": "Péchabou",
    "distanceBordeaux": 12.7,
    "densiteBornes": 3.3,
    "profilCommune": "bourg périurbain",
    "marcheImmobilier": "accessible",
    "tauxMaisonLabel": "majoritairement pavillonnaire"
  },
  {
    "nom": "Cépet",
    "slug": "cepet",
    "codeInsee": "31136",
    "codePostal": "31620",
    "population": 2389,
    "latitude": 43.7487,
    "longitude": 1.4368,
    "altitude": 140,
    "logements": 1062,
    "logementsMaison": 65,
    "prixM2Moyen": 2510,
    "vehiculesElectriques": 100,
    "croissanceVE": 27,
    "bornesPubliques": 9,
    "intercommunalite": "Communauté de Communes du Frontonnais",
    "canton": "Cépet",
    "distanceBordeaux": 16,
    "densiteBornes": 3.8,
    "profilCommune": "bourg périurbain",
    "marcheImmobilier": "intermédiaire",
    "tauxMaisonLabel": "majoritairement pavillonnaire"
  },
  {
    "nom": "Martres-Tolosane",
    "slug": "martres-tolosane",
    "codeInsee": "31324",
    "codePostal": "31220",
    "population": 2387,
    "latitude": 43.2052,
    "longitude": 0.994,
    "altitude": 269,
    "logements": 1061,
    "logementsMaison": 69,
    "prixM2Moyen": 2540,
    "vehiculesElectriques": 100,
    "croissanceVE": 27,
    "bornesPubliques": 9,
    "intercommunalite": "Communauté de Communes Cœur de Garonne",
    "canton": "Martres-Tolosane",
    "distanceBordeaux": 57.4,
    "densiteBornes": 3.8,
    "profilCommune": "bourg périurbain",
    "marcheImmobilier": "intermédiaire",
    "tauxMaisonLabel": "majoritairement pavillonnaire"
  },
  {
    "nom": "Saubens",
    "slug": "saubens",
    "codeInsee": "31533",
    "codePostal": "31600",
    "population": 2364,
    "latitude": 43.4799,
    "longitude": 1.3592,
    "altitude": 136,
    "logements": 1051,
    "logementsMaison": 61,
    "prixM2Moyen": 2140,
    "vehiculesElectriques": 100,
    "croissanceVE": 23,
    "bornesPubliques": 5,
    "intercommunalite": "Le Muretain Agglo",
    "canton": "Muret",
    "distanceBordeaux": 15.5,
    "densiteBornes": 2.1,
    "profilCommune": "bourg périurbain",
    "marcheImmobilier": "accessible",
    "tauxMaisonLabel": "majoritairement pavillonnaire"
  },
  {
    "nom": "Rouffiac-Tolosan",
    "slug": "rouffiac-tolosan",
    "codeInsee": "31462",
    "codePostal": "31180",
    "population": 2363,
    "latitude": 43.6638,
    "longitude": 1.5253,
    "altitude": 151,
    "logements": 1050,
    "logementsMaison": 61,
    "prixM2Moyen": 2510,
    "vehiculesElectriques": 95,
    "croissanceVE": 24,
    "bornesPubliques": 9,
    "intercommunalite": "Communauté de Communes du Volvestre",
    "canton": "Rouffiac-Tolosan",
    "distanceBordeaux": 9.3,
    "densiteBornes": 3.8,
    "profilCommune": "bourg périurbain",
    "marcheImmobilier": "intermédiaire",
    "tauxMaisonLabel": "majoritairement pavillonnaire"
  },
  {
    "nom": "Saint-Loup-Cammas",
    "slug": "saint-loup-cammas",
    "codeInsee": "31497",
    "codePostal": "31140",
    "population": 2334,
    "latitude": 43.6968,
    "longitude": 1.4786,
    "altitude": 152,
    "logements": 1037,
    "logementsMaison": 62,
    "prixM2Moyen": 2250,
    "vehiculesElectriques": 85,
    "croissanceVE": 26,
    "bornesPubliques": 9,
    "intercommunalite": "Toulouse Métropole",
    "canton": "Saint-Loup-Cammas",
    "distanceBordeaux": 10.6,
    "densiteBornes": 3.9,
    "profilCommune": "bourg périurbain",
    "marcheImmobilier": "accessible",
    "tauxMaisonLabel": "majoritairement pavillonnaire"
  },
  {
    "nom": "Lanta",
    "slug": "lanta",
    "codeInsee": "31271",
    "codePostal": "31570",
    "population": 2283,
    "latitude": 43.5573,
    "longitude": 1.6687,
    "altitude": 219,
    "logements": 1015,
    "logementsMaison": 93,
    "prixM2Moyen": 2360,
    "vehiculesElectriques": 107,
    "croissanceVE": 28,
    "bornesPubliques": 8,
    "intercommunalite": "Communauté de Communes du Volvestre",
    "canton": "Lanta",
    "distanceBordeaux": 18.8,
    "densiteBornes": 3.5,
    "profilCommune": "bourg périurbain",
    "marcheImmobilier": "accessible",
    "tauxMaisonLabel": "très pavillonnaire"
  },
  {
    "nom": "Saint-Sulpice-sur-Lèze",
    "slug": "saint-sulpice-sur-leze",
    "codeInsee": "31517",
    "codePostal": "31410",
    "population": 2277,
    "latitude": 43.3252,
    "longitude": 1.341,
    "altitude": 250,
    "logements": 1012,
    "logementsMaison": 65,
    "prixM2Moyen": 2000,
    "vehiculesElectriques": 96,
    "croissanceVE": 32,
    "bornesPubliques": 5,
    "intercommunalite": "Communauté de Communes du Volvestre",
    "canton": "Saint-Sulpice-sur-Lèze",
    "distanceBordeaux": 32.2,
    "densiteBornes": 2.2,
    "profilCommune": "bourg périurbain",
    "marcheImmobilier": "accessible",
    "tauxMaisonLabel": "majoritairement pavillonnaire"
  },
  {
    "nom": "Larra",
    "slug": "larra",
    "codeInsee": "31592",
    "codePostal": "31330",
    "population": 2273,
    "latitude": 43.7355,
    "longitude": 1.2223,
    "altitude": 141,
    "logements": 1010,
    "logementsMaison": 66,
    "prixM2Moyen": 2540,
    "vehiculesElectriques": 90,
    "croissanceVE": 26,
    "bornesPubliques": 5,
    "intercommunalite": "Communauté de Communes des Hauts Tolosains",
    "canton": "Larra",
    "distanceBordeaux": 23,
    "densiteBornes": 2.2,
    "profilCommune": "bourg périurbain",
    "marcheImmobilier": "intermédiaire",
    "tauxMaisonLabel": "majoritairement pavillonnaire"
  },
  {
    "nom": "Saint-Sauveur",
    "slug": "saint-sauveur",
    "codeInsee": "31516",
    "codePostal": "31790",
    "population": 2243,
    "latitude": 43.749,
    "longitude": 1.3947,
    "altitude": 130,
    "logements": 997,
    "logementsMaison": 55,
    "prixM2Moyen": 2440,
    "vehiculesElectriques": 84,
    "croissanceVE": 31,
    "bornesPubliques": 5,
    "intercommunalite": "Communauté de Communes du Volvestre",
    "canton": "Saint-Sauveur",
    "distanceBordeaux": 16.5,
    "densiteBornes": 2.2,
    "profilCommune": "bourg périurbain",
    "marcheImmobilier": "accessible",
    "tauxMaisonLabel": "mixte pavillonnaire-collectif"
  },
  {
    "nom": "Lévignac",
    "slug": "levignac",
    "codeInsee": "31297",
    "codePostal": "31530",
    "population": 2206,
    "latitude": 43.6646,
    "longitude": 1.2036,
    "altitude": 148,
    "logements": 980,
    "logementsMaison": 58,
    "prixM2Moyen": 2050,
    "vehiculesElectriques": 78,
    "croissanceVE": 31,
    "bornesPubliques": 5,
    "intercommunalite": "Communauté de Communes du Volvestre",
    "canton": "Lévignac",
    "distanceBordeaux": 20.5,
    "densiteBornes": 2.3,
    "profilCommune": "bourg périurbain",
    "marcheImmobilier": "accessible",
    "tauxMaisonLabel": "mixte pavillonnaire-collectif"
  },
  {
    "nom": "Pompertuzat",
    "slug": "pompertuzat",
    "codeInsee": "31429",
    "codePostal": "31450",
    "population": 2155,
    "latitude": 43.4958,
    "longitude": 1.5199,
    "altitude": 130,
    "logements": 958,
    "logementsMaison": 55,
    "prixM2Moyen": 2340,
    "vehiculesElectriques": 75,
    "croissanceVE": 26,
    "bornesPubliques": 9,
    "intercommunalite": "Communauté de Communes du Volvestre",
    "canton": "Pompertuzat",
    "distanceBordeaux": 13.6,
    "densiteBornes": 4.2,
    "profilCommune": "bourg périurbain",
    "marcheImmobilier": "accessible",
    "tauxMaisonLabel": "mixte pavillonnaire-collectif"
  },
  {
    "nom": "Sainte-Foy-de-Peyrolières",
    "slug": "sainte-foy-de-peyrolieres",
    "codeInsee": "31481",
    "codePostal": "31470",
    "population": 2088,
    "latitude": 43.4754,
    "longitude": 1.1362,
    "altitude": 146,
    "logements": 928,
    "logementsMaison": 56,
    "prixM2Moyen": 2570,
    "vehiculesElectriques": 95,
    "croissanceVE": 32,
    "bornesPubliques": 5,
    "intercommunalite": "Le Muretain Agglo",
    "canton": "Sainte-Foy-de-Peyrolières",
    "distanceBordeaux": 28.7,
    "densiteBornes": 2.4,
    "profilCommune": "bourg périurbain",
    "marcheImmobilier": "intermédiaire",
    "tauxMaisonLabel": "mixte pavillonnaire-collectif"
  },
  {
    "nom": "Flourens",
    "slug": "flourens",
    "codeInsee": "31184",
    "codePostal": "31130",
    "population": 2084,
    "latitude": 43.5975,
    "longitude": 1.5514,
    "altitude": 147,
    "logements": 926,
    "logementsMaison": 57,
    "prixM2Moyen": 2530,
    "vehiculesElectriques": 83,
    "croissanceVE": 32,
    "bornesPubliques": 9,
    "intercommunalite": "Toulouse Métropole",
    "canton": "Flourens",
    "distanceBordeaux": 8.7,
    "densiteBornes": 4.3,
    "profilCommune": "bourg périurbain",
    "marcheImmobilier": "intermédiaire",
    "tauxMaisonLabel": "mixte pavillonnaire-collectif"
  },
  {
    "nom": "Bagnères-de-Luchon",
    "slug": "bagneres-de-luchon",
    "codeInsee": "31042",
    "codePostal": "31110",
    "population": 2076,
    "latitude": 42.7492,
    "longitude": 0.6264,
    "altitude": 372,
    "logements": 923,
    "logementsMaison": 92,
    "prixM2Moyen": 2570,
    "vehiculesElectriques": 108,
    "croissanceVE": 22,
    "bornesPubliques": 7,
    "intercommunalite": "Communauté de Communes du Volvestre",
    "canton": "Bagnères-de-Luchon",
    "distanceBordeaux": 116,
    "densiteBornes": 3.4,
    "profilCommune": "bourg périurbain",
    "marcheImmobilier": "intermédiaire",
    "tauxMaisonLabel": "très pavillonnaire"
  },
  {
    "nom": "Lacroix-Falgarde",
    "slug": "lacroix-falgarde",
    "codeInsee": "31259",
    "codePostal": "31120",
    "population": 2030,
    "latitude": 43.5022,
    "longitude": 1.4256,
    "altitude": 150,
    "logements": 902,
    "logementsMaison": 60,
    "prixM2Moyen": 2450,
    "vehiculesElectriques": 92,
    "croissanceVE": 25,
    "bornesPubliques": 8,
    "intercommunalite": "Le Muretain Agglo",
    "canton": "Lacroix-Falgarde",
    "distanceBordeaux": 11.5,
    "densiteBornes": 3.9,
    "profilCommune": "bourg périurbain",
    "marcheImmobilier": "accessible",
    "tauxMaisonLabel": "majoritairement pavillonnaire"
  }
]
